README.md
setup.py
gdbundbrm/api_hs.py
gdbundbrm/api_rm.py
gdbundbrm/custom_views.py
gdbundbrm/mixins.py
gdbundbrm.egg-info/PKG-INFO
gdbundbrm.egg-info/SOURCES.txt
gdbundbrm.egg-info/dependency_links.txt
gdbundbrm.egg-info/requires.txt
gdbundbrm.egg-info/top_level.txt