Metadata-Version: 2.1
Name: gdbundbrm
Version: 1.0.10
Summary: integração API RM
Home-page: UNKNOWN
Author: Grupo Dom Bosco
Author-email: nti@undb.edu.br
License: MIT License
Keywords: RM
Platform: UNKNOWN
